[
  {
    "title": "Github",
    "desc": "全球 Git 分布式存储仓库",
    "tags": ["code"],
    "links": {
      "href": "https://www.github.com"
    }
  },
  {
    "title": "Material CSS Kit",
    "desc": "Materialize 风格的样式组件",
    "tags": ["code"],
    "links": {
      "href": "https://materializecss.com/"
    }
  },
  {
    "title": "I18n locales code",
    "icon": "fas fa-language",
    "desc": "翻译时对应的 code",
    "tags": ["code"],
    "links": {
      "href": "https://www.iana.org/assignments/language-subtag-registry/language-subtag-registry"
    }
  },
  {
    "title": "今日诗词 API",
    "desc": "诗词实时智能推荐 - 一言 API",
    "tags": ["code"],
    "links": {
      "href": "https://www.jinrishici.com"
    }
  },
  {
    "title": "Everything",
    "desc": "小巧，快速的搜索工具",
    "tags": ["win"],
    "links": {
      "href": "https://voidtools.com"
    }
  },
  {
    "title": "Rufus",
    "desc": "小巧的 U 盘启动，引导制作工具",
    "tags": ["win"],
    "links": {
      "git": "https://github.com/pbatard/rufus",
      "href": "https://rufus.ie"
    }
  },
  {
    "title": "OBS 直播工具",
    "desc": "开源直播工具",
    "tags": ["win", "mac", "linux"],
    "links": {
      "href": "https://obsproject.com/"
    }
  },
  {
    "title": "Cloc",
    "icon": "fas fa-tools",
    "desc": "统计代码行数的工具",
    "tags": ["win", "mac", "linux"],
    "links": {
      "git": "https://github.com/AlDanial/cloc"
    }
  },
  {
    "title": "百度脑图",
    "desc": "百度良心软件，在线脑图工具",
    "tags": ["web"],
    "links": {
      "href": "http://naotu.baidu.com/"
    }
  },
  {
    "title": "Figma",
    "desc": "在线原型设计工具",
    "tags": ["web"],
    "links": {
      "href": "https://www.figma.com"
    }
  },
  {
    "title": "Squoosh",
    "desc": "Web 技术图片压缩工具",
    "tags": ["web"],
    "links": {
      "href": "https://squoosh.app/"
    }
  },
  {
    "title": "TinyPNG",
    "desc": "TinyPNG能在完整保留透明度的同时将PNG图片压缩50-80%",
    "tags": ["web", "image"],
    "links": {
      "href": "https://tinypng.com/"
    }
  },
  {
    "title": "Removbg",
    "desc": "免费在线 AI 抠图神器，同时提供 API 和 PS 插件",
    "tags": ["web", "image"],
    "links": {
      "href": "https://www.remove.bg"
    }
  },
  {
    "title": "VectorLogoZone",
    "desc": "图标库",
    "tags": ["web", "icon"],
    "links": {
      "href": "https://www.vectorlogo.zone"
    }
  },
  {
    "title": "壁纸网站",
    "desc": "桌面、手机壁纸在线下载网站/社区",
    "tags": ["web", "wallpaper"],
    "links": {
      "href": "https://wall.alphacoders.com/"
    }
  },
  {
    "title": "FreeLogoDesgin",
    "desc": "方便，简单的免费 Logo 设计网站",
    "tags": ["web", "logo"],
    "links": {
      "href": "https://www.freelogodesign.org/"
    }
  },
  {
    "title": "SteamGridDB",
    "desc": "把其他平台的游戏一键导入到 Steam 中",
    "tags": ["game", "tool"],
    "links": {
      "href": "https://www.steamgriddb.com/manager",
      "git": "https://github.com/steamgriddb/steamgriddb-manager"
    }
  },
  {
    "title": "WarriorJS",
    "desc": "用代码玩的冒险游戏",
    "tags": ["game"],
    "links": {
      "href": "https://warrior.js.org/",
      "git": "https://github.com/olistic/warriorjs"
    }
  },
  {
    "title": "Regexper",
    "desc": "正则可视化工具",
    "tags": ["web"],
    "links": {
      "href": "https://regexper.com/",
      "gitlab": "https://gitlab.com/javallone/regexper-static"
    }
  },
  {
    "title": "JSON Schema Store",
    "desc": "JSON Schema 存储仓库",
    "tags": ["web"],
    "links": {
      "href": "http://schemastore.org/json/",
      "git": "https://github.com/schemastore/schemastore/"
    }
  },
  {
    "title": "Cemu Emulator",
    "desc": "Will U 模拟器",
    "tags": ["game", "tool"],
    "links": {
      "href": "https://cemu.info/"
    }
  },
  {
    "title": "HashTab",
    "desc": "右键，属性，hashtab，直接对比 MD5、SHA-1 值",
    "tags": ["win"],
    "links": {
      "href": "http://implbits.com/products/hashtab/"
    }
  },
  {
    "title": "Hand Brake",
    "desc": "开源免费视频转码软件，支持几乎所有格式",
    "tags": ["win", "mac", "linux", "video"],
    "links": {
      "href": "https://handbrake.fr/",
      "git": "https://github.com/HandBrake/HandBrake"
    }
  },
  {
    "title": "Screen To Gif",
    "desc": "开源免费录制编辑 Gif 的软件",
    "tags": ["win", "gif"],
    "links": {
      "href": "https://www.screentogif.com/",
      "git": "https://github.com/NickeManarin/ScreenToGif/"
    }
  },
  {
    "title": "Snipaste",
    "desc": "免费且功能强大的截图软件",
    "tags": ["win", "mac", "linux"],
    "links": {
      "href": "https://www.snipaste.com/"
    }
  },
  {
    "title": "ManicTime",
    "desc": "全平台记录使用应用时间的软件，基础版免费",
    "tags": ["win", "mac", "linux"],
    "links": {
      "href": "https://www.manictime.com/"
    }
  },
  {
    "title": "aText",
    "desc": "非常方便的预定制文本输入工具",
    "tags": ["win", "mac"],
    "links": {
      "href": "https://trankynam.com/atext/"
    }
  },
  {
    "title": "mouseinc",
    "desc": "小巧好用的全局鼠标手势",
    "tags": ["win", "tool"],
    "links": {
      "href": "https://shuax.com/project/mouseinc/"
    }
  }
]
